LICENSE
README.md
setup.py
elastic_dql/__init__.py
elastic_dql/config.py
elastic_dql/exceptions.py
elastic_dql/field.py
elastic_dql/query.py
elastic_dql/query_generator.py
elastic_dql/schema.py
elastic_dql/serializers.py
elastic_dql/urls.py
elastic_dql/utils.py
elastic_dql/views.py
elastic_dql.egg-info/PKG-INFO
elastic_dql.egg-info/SOURCES.txt
elastic_dql.egg-info/dependency_links.txt
elastic_dql.egg-info/not-zip-safe
elastic_dql.egg-info/requires.txt
elastic_dql.egg-info/top_level.txt